CHANGES.rst
CONTRIBUTORS.rst
DEVELOP.rst
LICENSE.rst
MANIFEST.in
README.rst
setup.cfg
setup.py
docs/README.rst
docs/ativar_facetada.png
docs/clonar.png
docs/clonar_form.png
docs/coluna_01.png
docs/coluna_02.png
docs/coluna_03.png
docs/coluna_04.png
docs/coluna_05.png
docs/config_facetada.png
docs/criterios_facetadas.png
docs/data_relatorio_field.png
docs/data_relatorio_index_metadata.png
docs/date_format.png
docs/estrutura_pastas.png
docs/legenda_tabela.png
docs/ministerio.png
docs/ministerio_relatorio_field.png
docs/ministerio_relatorio_field_config.png
docs/ministerio_relatorio_index_metadata.png
docs/palavra_chave.png
docs/path.png
docs/periodo.png
docs/relatorios.xml
docs/resultado.png
docs/tipo.png
docs/titulo.png
docs/visao_facetada_tabular.png
docs/visao_facetada_tabular_sumaria.png
docs/vocabularios_dinamicos.png
src/brasil/__init__.py
src/brasil/__init__.pyo
src/brasil.gov.newfieldcomplement.egg-info/PKG-INFO
src/brasil.gov.newfieldcomplement.egg-info/SOURCES.txt
src/brasil.gov.newfieldcomplement.egg-info/dependency_links.txt
src/brasil.gov.newfieldcomplement.egg-info/entry_points.txt
src/brasil.gov.newfieldcomplement.egg-info/namespace_packages.txt
src/brasil.gov.newfieldcomplement.egg-info/not-zip-safe
src/brasil.gov.newfieldcomplement.egg-info/requires.txt
src/brasil.gov.newfieldcomplement.egg-info/top_level.txt
src/brasil/gov/__init__.py
src/brasil/gov/newfieldcomplement/__init__.py
src/brasil/gov/newfieldcomplement/config.py
src/brasil/gov/newfieldcomplement/configure.zcml
src/brasil/gov/newfieldcomplement/dependencies.zcml
src/brasil/gov/newfieldcomplement/interfaces.py
src/brasil/gov/newfieldcomplement/patches.py
src/brasil/gov/newfieldcomplement/patches.zcml
src/brasil/gov/newfieldcomplement/permissions.zcml
src/brasil/gov/newfieldcomplement/setuphandlers.py
src/brasil/gov/newfieldcomplement/testing.py
src/brasil/gov/newfieldcomplement/upgrades.py
src/brasil/gov/newfieldcomplement/upgrades.zcml
src/brasil/gov/newfieldcomplement/vocabularies.py
src/brasil/gov/newfieldcomplement/vocabularies.zcml
src/brasil/gov/newfieldcomplement/browser/__init__.py
src/brasil/gov/newfieldcomplement/browser/__init__.pyo
src/brasil/gov/newfieldcomplement/browser/add_index_form.py
src/brasil/gov/newfieldcomplement/browser/configure.zcml
src/brasil/gov/newfieldcomplement/browser/dynamic_vocabularies_form.py
src/brasil/gov/newfieldcomplement/browser/faceted_tabular_config.py
