Metadata-Version: 2.1
Name: brasil.gov.newfieldcomplement
Version: 1.1.0
Summary: An add-on for Plone
Home-page: UNKNOWN
Author: PloneGovBr
Author-email: gov@plone.org.br
License: GPL version 2
Keywords: Python Plone
Platform: UNKNOWN
Classifier: Environment :: Web Environment
Classifier: Framework :: Plone
Classifier: Framework :: Plone :: 4.3
Classifier: Programming Language :: Python
Classifier: Programming Language :: Python :: 2.7
Classifier: Operating System :: OS Independent
Classifier: License :: OSI Approved :: GNU General Public License v2 (GPLv2)
Provides-Extra: test
